{
  "id": "3d-scan-social-app",
  "title": "ScanShare — 3D 扫描社交平台",
  "slug": "scanshare-3d-social",
  "category": "AR / 社交 / 创意工具",
  "date": "2025-08-28",
  "image": "https://images.unsplash.com/photo-1531266750466-9f0f6f5a3f2d?q=80&w=1200&h=800&auto=format&fit=crop",
    "intro":{
    "intro":"3D 扫描和分享正在成为下一波创作者经济的爆点，但现有工具复杂、昂贵、缺乏社交属性。创作者、商户和年轻用户要么困在专业软件的学习曲线里，要么受限于质量低下的“玩具级”应用。\nScanShare 是一款移动优先的 3D 扫描与社交平台，让任何人都能用手机一键生成高质量 3D 模型，并在内建的社区里分享、发现和变现。通过 手机端扫描 → 云端自动重建 → 社交展览与交易 的完整流程，ScanShare 把 3D 创作门槛降到和拍照一样低。",
    "market":["过去 6 个月，3D 扫描相关讨论量增长 75%","AR 社交应用下载量增长 120%","全球搜索“mobile 3D scanning”已达 5.4 万/月，且同比增长 42%"],
    "offer":["一键式手机扫描 + 自动化修复","云端高质量重建与快速预览","内建社交流和创作者社区","变现工具（付费下载、打赏、虚拟藏品）","扩展至电商 API，支持商户快速上架交互式 3D 商品"],
    "vision":"与 RealityCapture、CaptureApp、Sketchfab 等现有方案相比，ScanShare 的优势在于 端到端一体化：从扫描到分享和变现，不再需要切换多个工具，也不必为昂贵的 SaaS 买单。 让 3D 内容创作与分享像拍照和发朋友圈一样简单，成为创作者经济和社交娱乐的下一块增长引擎。"
  },
  "one_minute_introduction": {
  
    "painpoint": "用户希望轻松生成并分享高质量的 3D 扫描（人物、物品、场景），但现有工具复杂、成本高且社交属性弱。",
    "value": "通过手机端一键扫描 + 云端重建 + 社交展览，降低 3D 内容创建门槛，提升分享体验和创作发现。",
    "solution": "提供移动端自动化扫描流程、轻量化后处理、嵌入式社交流、以及作品商用/版税分发路径。"
  },
  "metrics": {
    "mentions": 1234,
    "growth_rate": "+48%",
    "severity": 7.1,
    "opportunity": 8.6,
    "sentiment": "mixed"
  },
  "overview": {
    "key_insights_ai": [
      "社交用户对“可交互3D内容”的兴趣快速增长，尤其在创作者与小型品牌群体中。",
      "手机硬件已能满足基础多视角扫描，但复原质量与自动化仍是痛点。",
      "创作者希望可变现渠道（tips、付费下载、NFT/数字藏品）与更简单的工作流。"
    ],
    "top_subreddits": [
      "r/3Dprinting",
      "r/photogrammetry",
      "r/AR_MR",
      "r/IndieWeb"
    ],
    "summary": "ScanShare 面向创作者与兴趣社群（手工艺、二手古董、时装、虚拟角色），通过低门槛扫描 + 社交分发实现快速内容增长与长期变现。"
  },
  "customer": [
      {
        "name": "独立3D创作者",
        "behavior": "在 Reddit /r/3Dmodeling、/r/indieDev 等社区活跃，频繁讨论如何提高工作流效率。",
        "pain_points": [
          {
            "description": "后处理和修复 3D 扫描模型耗时过长，严重影响创作效率。",
            "source": "https://reddit.com/r/3Dmodeling/comments/xxxxxx (高赞评论：'fixing meshes takes me longer than scanning itself')"
          },
          {
            "description": "缺乏一体化工具链，需要在多个软件之间切换。",
            "source": "https://reddit.com/r/indieDev/comments/yyyyyy"
          },
          {
            "description": "作品难以获得曝光，缺少便捷的社交分享通道。",
            "source": "https://reddit.com/r/3Dmodeling/comments/zzzzzz"
          }
        ]
      },
      {
        "name": "中小商户（如古董/手工艺品卖家）",
        "behavior": "在 /r/Entrepreneur、/r/smallbusiness 讨论如何用 3D 提升产品展示和转化率。",
        "pain_points": [
          {
            "description": "传统商品摄影难以展示细节，导致转化率低。",
            "source": "https://reddit.com/r/Entrepreneur/comments/aaaaaa"
          },
          {
            "description": "现有 3D 展示 SaaS 工具价格昂贵，不适合小商户。",
            "source": "https://reddit.com/r/smallbusiness/comments/bbbbbb"
          },
          {
            "description": "缺乏简单的 3D 上架/嵌入解决方案。",
            "source": "https://reddit.com/r/Entrepreneur/comments/cccccc"
          }
        ]
      },
      {
        "name": "年轻社交用户",
        "behavior": "在 Reddit /r/socialmedia、Twitter (#3Dfilter、#ARfun) 等话题下活跃，喜欢尝试新奇滤镜和特效。",
        "pain_points": [
          {
            "description": "现有滤镜内容同质化，缺少个性化玩法。",
            "source": "https://twitter.com/search?q=%233Dfilter"
          },
          {
            "description": "制作 3D 内容门槛高，没有一键式工具。",
            "source": "https://reddit.com/r/socialmedia/comments/dddddd"
          },
          {
            "description": "社交平台支持不足，3D 分享体验割裂。",
            "source": "https://twitter.com/search?q=%23ARfun"
          }
        ]
      }
    ],
  "competition": {
    "competitors": [
      {
        "name": "RealityCapture (example)",
        "url": "https://example-rc.com",
        "pricing": "桌面授权 / 高端设备，需要专业知识",
        "strengths": [
          "重建精度高",
          "行业认可"
        ],
        "weaknesses": [
          "复杂、成本高、非社交化"
        ]
      },
      {
        "name": "CaptureApp (example mobile)",
        "url": "https://example-capture.com",
        "pricing": "免费 + 内购",
        "strengths": [
          "移动端友好",
          "易上手"
        ],
        "weaknesses": [
          "模型质量差、无内建社交与变现"
        ]
      },
      {
        "name": "Sketchfab",
        "url": "https://sketchfab.com",
        "pricing": "免费 / 订阅 / 商业授权",
        "strengths": [
          "社区和托管能力",
          "嵌入展示"
        ],
        "weaknesses": [
          "不是一体化的扫描到分享工作流"
        ]
      }
    ],
    "differentiation": "ScanShare 将“一键移动扫描 → 云端自动重建 → 社交流 + 变现”整合成端到端产品，并提供低延迟预览与创作者分成机制。"
  },
  "business_model": {
    "revenue_streams": [
      "订阅（Pro 功能：高清重建、商业许可）",
      "交易佣金（作品商店 / 购买 3D 资产）",
      "企业 API（电商 / 展示嵌入）",
      "广告与品牌合作（展示赞助）"
    ],
    "pricing_strategy": "Freemium（免费基础重建） + Pro 月费 $9.99 / 年费 $79.99",
    "expansion_opportunities": [
      "将 3D 模型授权给 AR 广告与电商平台",
      "B2B 白标授权给博物馆、电商和地产"
    ]
  },
  "trends": [
    {
      "keyword": "mobile 3d scanning",
      "keyword_summary_ai": "移动 3D 扫描搜索量与工具兴趣在近三年显著增加，用户更多寻求 'easy' 与 'quick' 解决方案。",
      "monthly_global_search_volume": 54000,
      "year_over_year_growth_rate": 42,
      "average_cost_per_click": 2.8,
      "keyword_competition_level": "Medium",
      "trendData": {
        "2021": 12000,
        "2022": 18500,
        "2023": 26000,
        "2024": 38000,
        "2025": 54000
      }
    },
    {
      "keyword": "3d model marketplace",
      "keyword_summary_ai": "市场对高质量可商用 3D 资产需求增长，尤其在 AR 电商与元宇宙创作中。",
      "monthly_global_search_volume": 16000,
      "year_over_year_growth_rate": 28,
      "average_cost_per_click": 4.6,
      "keyword_competition_level": "High",
      "trendData": {
        "2021": 8000,
        "2022": 9500,
        "2023": 11500,
        "2024": 13000,
        "2025": 16000
      }
    }
  ],
  "analysis": [
    {
      "factor": "Market Timing",
      "score": 9,
      "reason_ai": [
        "智能手机摄像头与移动算力近年快速提升，支持高精度 3D 扫描在消费端普及。",
        "创作者经济与虚拟内容（AR/VR、数字藏品）的市场热度持续上升，社交玩法进入成熟期。",
        "WebGPU / Three.js 等前端图形渲染框架逐渐成熟，使得 Web App 体验接近原生应用。"
      ],
      "source": [
        "https://example-report-mobile-camera.com",
        "https://example-ar-market.com",
        "https://threejs.org/"
      ]
    },
    {
      "factor": "Open Source & Tech Feasibility",
      "score": 8,
      "reason_ai": [
        "开源项目如 `colmap`、`openMVS` 提供了成熟的 3D 重建算法，大幅降低研发成本。",
        "近期社区在 `NeRF` 与 `Gaussian Splatting` 等新技术上持续迭代，保证可行性与创新性。",
        "GitHub 上相关 3D 扫描/重建仓库活跃度高，意味着开发者生态具备协同潜力。"
      ],
      "source": [
        "https://github.com/colmap/colmap",
        "https://github.com/cdcseacave/openMVS",
        "https://github.com/nerfstudio-project/nerfstudio"
      ]
    },
    {
      "factor": "Competitive Advantage",
      "score": 7,
      "reason_ai": [
        "端到端一体化流程（扫描 → 重建 → 社交分享）显著降低用户门槛，形成差异化。",
        "传统专业工具偏向学术/企业用户，而本产品聚焦于轻量化 + 社交化，切入点不同。",
        "但在精度和自动化上，短期仍需依赖云端算力，成本控制是关键挑战。"
      ],
      "source": [
        "https://example-competitor-analysis.com"
      ]
    },
    {
      "factor": "Monetization Feasibility",
      "score": 8,
      "reason_ai": [
        "创作者与中小商户对快速 3D 展示工具存在付费意愿（订阅 / SaaS / 市场分成）。",
        "社交场景增加了用户粘性，可引入道具、滤镜、虚拟资产的内购模式。",
        "已有用户调研和社交媒体讨论表明市场教育成本低，可快速转化早期用户。"
      ],
      "source": [
        "https://example-market-validation.com"
      ]
    }
  ],
  "risks": [
    {
      "type": "技术风险",
      "description": "自动化重建质量达不到商业化要求或成本过高。",
      "mitigation": "采用渐进式上采样策略，先服务低成本场景（小物件），并优化云批处理。"
    },
    {
      "type": "市场风险",
      "description": "用户习惯未形成，社交黏性不足导致留存率低。",
      "mitigation": "鼓励创作者通过收入分成、挑战赛和社群激励快速形成核心用户群。"
    },
    {
      "type": "法规/隐私风险",
      "description": "人像扫描可能涉及隐私与肖像权。",
      "mitigation": "加入隐私提示、授权流程与人像模糊/同意策略；法律咨询。"
    }
  ]
}
